README.md
setup.py
umnet_ncs_instances/__init__.py
umnet_ncs_instances/instances.py
umnet_ncs_instances/types.py
umnet_ncs_instances.egg-info/PKG-INFO
umnet_ncs_instances.egg-info/SOURCES.txt
umnet_ncs_instances.egg-info/dependency_links.txt
umnet_ncs_instances.egg-info/requires.txt
umnet_ncs_instances.egg-info/top_level.txt