Metadata-Version: 2.1
Name: umnet-ncs-instances
Version: 0.0.22
Summary: Python object representing NSO service or device instances.
Home-page: https://gitlab.umich.edu/its-inf-net/umnet-ncs-instances
Author: University of Michigan
Author-email: amylieb@umich.edu
License: UNKNOWN
Platform: UNKNOWN
Classifier: Programming Language :: Python :: 3
Classifier: Operating System :: OS Independent
Requires-Python: >=3.6
